{
  "${ModID}:Nails": {
    "NAME": "Nails",
    "DESCRIPTIONS": [
      "At the start of its turn, loses #b",
      " HP."
    ]
  },
  "${ModID}:EnergizedCranky": {
    "NAME": "Energized",
    "DESCRIPTIONS": [
      "Gain #b",
      " additional [E] next turn."
    ]
  },
  "${ModID}:Cogwheel": {
    "NAME": "Cogwheel",
    "DESCRIPTIONS": [
      "At the start of your turn, gain #b",
      " charge."
    ]
  },
  "${ModID}:InertiaPower": {
    "NAME": "Inertia",
    "DESCRIPTIONS": [
      "Whenever you #yWind #yUp, you have #b",
      " additional Strength until you next #ySpin. NL You currently have #b",
      " additional Strength."
    ]
  },
  "${ModID}:Battery": {
    "NAME": "Battery",
    "DESCRIPTIONS": [
      "The next time you try to #ySpin without enough charge, #ySpinning costs no charge",
      "The next #b",
      " times you try to #ySpin without enough charge, #ySpinning costs no charge."
    ]
  },
  "${ModID}:EfficiencyPower": {
    "NAME": "Efficiency",
    "DESCRIPTIONS": [
      "When #yParts are activated, they activate #b",
      " additional time.",
      " additional times."
    ]
  },
  "${ModID}:GreasedCogsPower": {
    "NAME": "Greased Cogs",
    "DESCRIPTIONS": [
      "Next turn, #yWinding #yUp will provide #b",
      " times as much charge."
    ]
  },
  "${ModID}:Twisty": {
    "NAME": "Twisty",
    "DESCRIPTIONS": [
      "This turn, #yWinding #yUp provides #b",
      " times as much charge."
    ]
  },
  "${ModID}:Dizzy": {
    "NAME": "Dizzy",
    "DESCRIPTIONS": [
      "When attacked, loses #b",
      " #yStrength."
    ]
  },
  "${ModID}:PerpetualFormPower": {
    "NAME": "Perpetual",
    "DESCRIPTIONS": [
      "At the start of your turn, lose ",
      ". Cards can be played with charge, using #b",
      " charge per energy."
    ]
  },
  "${ModID}:Proficiency": {
    "NAME": "Proficiency",
    "DESCRIPTIONS": [
      "Increases the effectiveness of Tools by #b",
      "."
    ]
  },
  "${ModID}:ScannerPower": {
    "NAME": "Scanner",
    "DESCRIPTIONS": [
      "Whenever you play a card, #yAttune it #b",
      " time.",
      " times."
    ]
  },
  "${ModID}:WindOnHit": {
    "NAME": "Kinetic Servo",
    "DESCRIPTIONS": [
      "When attacked, #yWinds #yUp #b",
      "."
    ]
  },
  "${ModID}:Glare": {
    "NAME": "Vexing Glare",
    "DESCRIPTIONS": [
      "Whenever #yParts are activated, deal #b",
      " damage to ALL enemies."
    ]
  },
  "${ModID}:DiligentWork": {
    "NAME": "Diligent Work",
    "DESCRIPTIONS": [
      "At the start of your turn, #yUse #b",
      " time.",
      " times."
    ]
  },
  "${ModID}:PeepTheHaul": {
    "NAME": "Peep the Haul!",
    "DESCRIPTIONS": [
      "At the start of your turn, if you have no #yBatteries, gain a #yBattery",
      "At the start of your turn, if you have fewer than #b",
      " #yBatteries, gain #yBatteries until you have #b",
      "."
    ]
  },
  "${ModID}:Sawblade": {
    "NAME": "Sawblade",
    "DESCRIPTIONS": [
      "Whenever you draw a #ySpinner, draw #b",
      " card.",
      " cards."
    ]
  }
}